{
  "group": "road",
  "overmap_terrain": "city_road",
  "fill_terrain": "t_pavement",
  "comment": "13x13 city road with sidewalks",
  "floors": {
    "0": [
      "SSRRRRCRRRRSS",
      "SSRRRRCRRRRSS",
      "RRRRRRCRRRRSS",
      "RRRRRRCRRRRSS",
      "RRRRRRCRRRRSS",
      "RRRRRRCRRRRSS",
      "CCCCCCCRRRRSS",
      "RRRRRRCRRRRSS",
      "RRRRRRCRRRRSS",
      "RRRRRRCRRRRSS",
      "RRRRRRCRRRRSS",
      "SSRRRRCRRRRSS",
      "SSRRRRCRRRRSS"
    ]
  },
  "terrain": {
    "S": "t_sidewalk",
    "R": "t_pavement",
    "C": "t_pavement_y"
  },
    "furniture": {
  }
}
